NeuronsMemoryTestPipeline/FRT_metric.py
NeuronsMemoryTestPipeline/MRT_free_recall_metric.py
NeuronsMemoryTestPipeline/MRT_recognition_metric.py
NeuronsMemoryTestPipeline/MRT_text_processing.py
NeuronsMemoryTestPipeline/QA_modules.py
NeuronsMemoryTestPipeline/__init__.py
NeuronsMemoryTestPipeline/constants.py
NeuronsMemoryTestPipeline/try.py
neuronsmemorytestpipeline-0.2.6.dist-info/LICENSE
neuronsmemorytestpipeline-0.2.6.dist-info/METADATA
neuronsmemorytestpipeline-0.2.6.dist-info/WHEEL
neuronsmemorytestpipeline-0.2.6.dist-info/RECORD
