Metadata-Version: 2.3
Name: NeuronsMemoryTestPipeline
Version: 0.2.6
Summary: Package provides QA, MRT and FRT metrics calculation for frt and mrt scores.
License: MIT
Keywords: metrics,QA,MRT,FRT,freerecall
Author: Irina White
Author-email: i.white@neuronsinc.com
Requires-Python: >=3.8,<4.0
Classifier: License :: OSI Approved :: MIT License
Classifier: Operating System :: OS Independent
Classifier: Programming Language :: Python :: 3
Classifier: Programming Language :: Python :: 3.8
Classifier: Programming Language :: Python :: 3.9
Classifier: Programming Language :: Python :: 3.10
Classifier: Programming Language :: Python :: 3.11
Classifier: Programming Language :: Python :: 3.12
Classifier: Programming Language :: Python :: 3.13
Requires-Dist: fuzzywuzzy
Requires-Dist: ipywidgets
Requires-Dist: numpy
Requires-Dist: openpyxl
Requires-Dist: pandas
Requires-Dist: python-Levenshtein
Requires-Dist: tqdm
Project-URL: Homepage, https://github.com/neurons-inc/neurons_metrics_package
Project-URL: Repository, https://github.com/neurons-inc/neurons_metrics_package
